{
  "configVersion": 1,
  "timestamp": 1764321752778,
  "index": "https://looted.github.io/bizzwords/index.csr.html",
  "assetGroups": [
    {
      "name": "app",
      "installMode": "prefetch",
      "updateMode": "prefetch",
      "cacheQueryOptions": {
        "ignoreVary": true
      },
      "urls": [
        "https://looted.github.io/bizzwords/chunk-4WL5KJUM.js",
        "https://looted.github.io/bizzwords/chunk-5LFCGYTW.js",
        "https://looted.github.io/bizzwords/chunk-DPPTIC4G.js",
        "https://looted.github.io/bizzwords/chunk-G2ZFNDAC.js",
        "https://looted.github.io/bizzwords/chunk-KS3PWG4I.js",
        "https://looted.github.io/bizzwords/favicon.ico",
        "https://looted.github.io/bizzwords/index.csr.html",
        "https://looted.github.io/bizzwords/index.html",
        "https://looted.github.io/bizzwords/main-BPGW77ZI.js",
        "https://looted.github.io/bizzwords/manifest.webmanifest",
        "https://looted.github.io/bizzwords/styles-BIIUBW6Z.css",
        "https://looted.github.io/bizzwords/worker-FORKZ3OH.js"
      ],
      "patterns": []
    },
    {
      "name": "assets",
      "installMode": "lazy",
      "updateMode": "prefetch",
      "cacheQueryOptions": {
        "ignoreVary": true
      },
      "urls": [
        "https://looted.github.io/bizzwords/android-chrome-192x192.png",
        "https://looted.github.io/bizzwords/android-chrome-512x512.png",
        "https://looted.github.io/bizzwords/android/android-launchericon-144-144.png",
        "https://looted.github.io/bizzwords/android/android-launchericon-192-192.png",
        "https://looted.github.io/bizzwords/android/android-launchericon-48-48.png",
        "https://looted.github.io/bizzwords/android/android-launchericon-512-512.png",
        "https://looted.github.io/bizzwords/android/android-launchericon-72-72.png",
        "https://looted.github.io/bizzwords/android/android-launchericon-96-96.png",
        "https://looted.github.io/bizzwords/apple-touch-icon.png",
        "https://looted.github.io/bizzwords/favicon-16x16.png",
        "https://looted.github.io/bizzwords/favicon-32x32.png",
        "https://looted.github.io/bizzwords/ios/100.png",
        "https://looted.github.io/bizzwords/ios/1024.png",
        "https://looted.github.io/bizzwords/ios/114.png",
        "https://looted.github.io/bizzwords/ios/120.png",
        "https://looted.github.io/bizzwords/ios/128.png",
        "https://looted.github.io/bizzwords/ios/144.png",
        "https://looted.github.io/bizzwords/ios/152.png",
        "https://looted.github.io/bizzwords/ios/16.png",
        "https://looted.github.io/bizzwords/ios/167.png",
        "https://looted.github.io/bizzwords/ios/180.png",
        "https://looted.github.io/bizzwords/ios/192.png",
        "https://looted.github.io/bizzwords/ios/20.png",
        "https://looted.github.io/bizzwords/ios/256.png",
        "https://looted.github.io/bizzwords/ios/29.png",
        "https://looted.github.io/bizzwords/ios/32.png",
        "https://looted.github.io/bizzwords/ios/40.png",
        "https://looted.github.io/bizzwords/ios/50.png",
        "https://looted.github.io/bizzwords/ios/512.png",
        "https://looted.github.io/bizzwords/ios/57.png",
        "https://looted.github.io/bizzwords/ios/58.png",
        "https://looted.github.io/bizzwords/ios/60.png",
        "https://looted.github.io/bizzwords/ios/64.png",
        "https://looted.github.io/bizzwords/ios/72.png",
        "https://looted.github.io/bizzwords/ios/76.png",
        "https://looted.github.io/bizzwords/ios/80.png",
        "https://looted.github.io/bizzwords/ios/87.png",
        "https://looted.github.io/bizzwords/windows11/LargeTile.scale-100.png",
        "https://looted.github.io/bizzwords/windows11/LargeTile.scale-125.png",
        "https://looted.github.io/bizzwords/windows11/LargeTile.scale-150.png",
        "https://looted.github.io/bizzwords/windows11/LargeTile.scale-200.png",
        "https://looted.github.io/bizzwords/windows11/LargeTile.scale-400.png",
        "https://looted.github.io/bizzwords/windows11/SmallTile.scale-100.png",
        "https://looted.github.io/bizzwords/windows11/SmallTile.scale-125.png",
        "https://looted.github.io/bizzwords/windows11/SmallTile.scale-150.png",
        "https://looted.github.io/bizzwords/windows11/SmallTile.scale-200.png",
        "https://looted.github.io/bizzwords/windows11/SmallTile.scale-400.png",
        "https://looted.github.io/bizzwords/windows11/SplashScreen.scale-100.png",
        "https://looted.github.io/bizzwords/windows11/SplashScreen.scale-125.png",
        "https://looted.github.io/bizzwords/windows11/SplashScreen.scale-150.png",
        "https://looted.github.io/bizzwords/windows11/SplashScreen.scale-200.png",
        "https://looted.github.io/bizzwords/windows11/SplashScreen.scale-400.png",
        "https://looted.github.io/bizzwords/windows11/Square150x150Logo.scale-100.png",
        "https://looted.github.io/bizzwords/windows11/Square150x150Logo.scale-125.png",
        "https://looted.github.io/bizzwords/windows11/Square150x150Logo.scale-150.png",
        "https://looted.github.io/bizzwords/windows11/Square150x150Logo.scale-200.png",
        "https://looted.github.io/bizzwords/windows11/Square150x150Logo.scale-400.png",
        "https://looted.github.io/bizzwords/windows11/Square44x44Logo.altform-lightunplated_targetsize-16.png",
        "https://looted.github.io/bizzwords/windows11/Square44x44Logo.altform-lightunplated_targetsize-20.png",
        "https://looted.github.io/bizzwords/windows11/Square44x44Logo.altform-lightunplated_targetsize-24.png",
        "https://looted.github.io/bizzwords/windows11/Square44x44Logo.altform-lightunplated_targetsize-256.png",
        "https://looted.github.io/bizzwords/windows11/Square44x44Logo.altform-lightunplated_targetsize-30.png",
        "https://looted.github.io/bizzwords/windows11/Square44x44Logo.altform-lightunplated_targetsize-32.png",
        "https://looted.github.io/bizzwords/windows11/Square44x44Logo.altform-lightunplated_targetsize-36.png",
        "https://looted.github.io/bizzwords/windows11/Square44x44Logo.altform-lightunplated_targetsize-40.png",
        "https://looted.github.io/bizzwords/windows11/Square44x44Logo.altform-lightunplated_targetsize-44.png",
        "https://looted.github.io/bizzwords/windows11/Square44x44Logo.altform-lightunplated_targetsize-48.png",
        "https://looted.github.io/bizzwords/windows11/Square44x44Logo.altform-lightunplated_targetsize-60.png",
        "https://looted.github.io/bizzwords/windows11/Square44x44Logo.altform-lightunplated_targetsize-64.png",
        "https://looted.github.io/bizzwords/windows11/Square44x44Logo.altform-lightunplated_targetsize-72.png",
        "https://looted.github.io/bizzwords/windows11/Square44x44Logo.altform-lightunplated_targetsize-80.png",
        "https://looted.github.io/bizzwords/windows11/Square44x44Logo.altform-lightunplated_targetsize-96.png",
        "https://looted.github.io/bizzwords/windows11/Square44x44Logo.altform-unplated_targetsize-16.png",
        "https://looted.github.io/bizzwords/windows11/Square44x44Logo.altform-unplated_targetsize-20.png",
        "https://looted.github.io/bizzwords/windows11/Square44x44Logo.altform-unplated_targetsize-24.png",
        "https://looted.github.io/bizzwords/windows11/Square44x44Logo.altform-unplated_targetsize-256.png",
        "https://looted.github.io/bizzwords/windows11/Square44x44Logo.altform-unplated_targetsize-30.png",
        "https://looted.github.io/bizzwords/windows11/Square44x44Logo.altform-unplated_targetsize-32.png",
        "https://looted.github.io/bizzwords/windows11/Square44x44Logo.altform-unplated_targetsize-36.png",
        "https://looted.github.io/bizzwords/windows11/Square44x44Logo.altform-unplated_targetsize-40.png",
        "https://looted.github.io/bizzwords/windows11/Square44x44Logo.altform-unplated_targetsize-44.png",
        "https://looted.github.io/bizzwords/windows11/Square44x44Logo.altform-unplated_targetsize-48.png",
        "https://looted.github.io/bizzwords/windows11/Square44x44Logo.altform-unplated_targetsize-60.png",
        "https://looted.github.io/bizzwords/windows11/Square44x44Logo.altform-unplated_targetsize-64.png",
        "https://looted.github.io/bizzwords/windows11/Square44x44Logo.altform-unplated_targetsize-72.png",
        "https://looted.github.io/bizzwords/windows11/Square44x44Logo.altform-unplated_targetsize-80.png",
        "https://looted.github.io/bizzwords/windows11/Square44x44Logo.altform-unplated_targetsize-96.png",
        "https://looted.github.io/bizzwords/windows11/Square44x44Logo.scale-100.png",
        "https://looted.github.io/bizzwords/windows11/Square44x44Logo.scale-125.png",
        "https://looted.github.io/bizzwords/windows11/Square44x44Logo.scale-150.png",
        "https://looted.github.io/bizzwords/windows11/Square44x44Logo.scale-200.png",
        "https://looted.github.io/bizzwords/windows11/Square44x44Logo.scale-400.png",
        "https://looted.github.io/bizzwords/windows11/Square44x44Logo.targetsize-16.png",
        "https://looted.github.io/bizzwords/windows11/Square44x44Logo.targetsize-20.png",
        "https://looted.github.io/bizzwords/windows11/Square44x44Logo.targetsize-24.png",
        "https://looted.github.io/bizzwords/windows11/Square44x44Logo.targetsize-256.png",
        "https://looted.github.io/bizzwords/windows11/Square44x44Logo.targetsize-30.png",
        "https://looted.github.io/bizzwords/windows11/Square44x44Logo.targetsize-32.png",
        "https://looted.github.io/bizzwords/windows11/Square44x44Logo.targetsize-36.png",
        "https://looted.github.io/bizzwords/windows11/Square44x44Logo.targetsize-40.png",
        "https://looted.github.io/bizzwords/windows11/Square44x44Logo.targetsize-44.png",
        "https://looted.github.io/bizzwords/windows11/Square44x44Logo.targetsize-48.png",
        "https://looted.github.io/bizzwords/windows11/Square44x44Logo.targetsize-60.png",
        "https://looted.github.io/bizzwords/windows11/Square44x44Logo.targetsize-64.png",
        "https://looted.github.io/bizzwords/windows11/Square44x44Logo.targetsize-72.png",
        "https://looted.github.io/bizzwords/windows11/Square44x44Logo.targetsize-80.png",
        "https://looted.github.io/bizzwords/windows11/Square44x44Logo.targetsize-96.png",
        "https://looted.github.io/bizzwords/windows11/StoreLogo.scale-100.png",
        "https://looted.github.io/bizzwords/windows11/StoreLogo.scale-125.png",
        "https://looted.github.io/bizzwords/windows11/StoreLogo.scale-150.png",
        "https://looted.github.io/bizzwords/windows11/StoreLogo.scale-200.png",
        "https://looted.github.io/bizzwords/windows11/StoreLogo.scale-400.png",
        "https://looted.github.io/bizzwords/windows11/Wide310x150Logo.scale-100.png",
        "https://looted.github.io/bizzwords/windows11/Wide310x150Logo.scale-125.png",
        "https://looted.github.io/bizzwords/windows11/Wide310x150Logo.scale-150.png",
        "https://looted.github.io/bizzwords/windows11/Wide310x150Logo.scale-200.png",
        "https://looted.github.io/bizzwords/windows11/Wide310x150Logo.scale-400.png"
      ],
      "patterns": []
    },
    {
      "name": "vocabulary",
      "installMode": "prefetch",
      "updateMode": "prefetch",
      "cacheQueryOptions": {
        "ignoreVary": true
      },
      "urls": [
        "https://looted.github.io/bizzwords/hr_eng_pl/hr_vocabulary_list_sample.csv",
        "https://looted.github.io/bizzwords/hr_eng_pl/hr_vocabulary_part2_fixed.csv",
        "https://looted.github.io/bizzwords/hr_eng_pl/hr_vocabulary_part3.csv.txt",
        "https://looted.github.io/bizzwords/hr_eng_pl/vocabulary.json"
      ],
      "patterns": []
    }
  ],
  "dataGroups": [],
  "hashTable": {
    "https://looted.github.io/bizzwords/android-chrome-192x192.png": "49794d6762c319009e4968c02dd2bbb04a52bf78",
    "https://looted.github.io/bizzwords/android-chrome-512x512.png": "3d76ed3e44f57711cd8f15ec57e3e634e1ee3747",
    "https://looted.github.io/bizzwords/android/android-launchericon-144-144.png": "b8353db625e8525effc2342cc05a80bf52758675",
    "https://looted.github.io/bizzwords/android/android-launchericon-192-192.png": "d817709e32dd5432b999afd08f46fd92d63d429e",
    "https://looted.github.io/bizzwords/android/android-launchericon-48-48.png": "8c3a950e4ac87c3eaa2983c4deefcbedf8aac18a",
    "https://looted.github.io/bizzwords/android/android-launchericon-512-512.png": "b3e3b35559fd519ae9b484a814fb895ec7403e50",
    "https://looted.github.io/bizzwords/android/android-launchericon-72-72.png": "8152c13d0cf1aec370a37730bf9d57989e47b59b",
    "https://looted.github.io/bizzwords/android/android-launchericon-96-96.png": "22fb8f3f909f01192009aae30ccdbf3445a260dc",
    "https://looted.github.io/bizzwords/apple-touch-icon.png": "142746761f29d96042d1e82684d5ce80b92f3252",
    "https://looted.github.io/bizzwords/chunk-4WL5KJUM.js": "5594e4eaab7fa441bb0b91a031a869b14c4e9e4b",
    "https://looted.github.io/bizzwords/chunk-5LFCGYTW.js": "5798ab1ee70fa43fe55c8cadc519d011ae3d7ff8",
    "https://looted.github.io/bizzwords/chunk-DPPTIC4G.js": "f52419745622b0d0601eeca1c856dcd3d6d178e7",
    "https://looted.github.io/bizzwords/chunk-G2ZFNDAC.js": "0305e6d3b45ff1191673933dd3d629d953b72cb3",
    "https://looted.github.io/bizzwords/chunk-KS3PWG4I.js": "5db1fdaed050de2866d9b758ff14d016e31395c0",
    "https://looted.github.io/bizzwords/favicon-16x16.png": "d1108cdba81a226bd69f5685d7a18bbc21c41caa",
    "https://looted.github.io/bizzwords/favicon-32x32.png": "0c6601f056b560471ba1799ba41db599ee720625",
    "https://looted.github.io/bizzwords/favicon.ico": "f8495e50a2b402964c65ac21353aa0a047e11676",
    "https://looted.github.io/bizzwords/hr_eng_pl/hr_vocabulary_list_sample.csv": "0fa6260526fcea2ad3a1162e04af630205999bc2",
    "https://looted.github.io/bizzwords/hr_eng_pl/hr_vocabulary_part2_fixed.csv": "e0cdf39c4ba2e2a63bfee249656f8ef6702c339c",
    "https://looted.github.io/bizzwords/hr_eng_pl/hr_vocabulary_part3.csv.txt": "3571e499c56cb43110f33a3123910b1dc766f94d",
    "https://looted.github.io/bizzwords/hr_eng_pl/vocabulary.json": "2e963c4075c97beb958f01f1a291624dfa706273",
    "https://looted.github.io/bizzwords/index.csr.html": "0a45d1bd6c1d262a39a7fe702e55bffc9ee23bfd",
    "https://looted.github.io/bizzwords/index.html": "9c4384e43f95dab5070fbe34abe8f21e56cac989",
    "https://looted.github.io/bizzwords/ios/100.png": "c5e3882adf978501d070c28c537b9c9779f2193d",
    "https://looted.github.io/bizzwords/ios/1024.png": "9ab4f821a5cdc83fb7d89c8b295a9cdd579b9b7b",
    "https://looted.github.io/bizzwords/ios/114.png": "79ff85d85af41952bdda2b1c77a934ab1417d8d6",
    "https://looted.github.io/bizzwords/ios/120.png": "bd2b3d0301e814112900c7844b008709441ed24d",
    "https://looted.github.io/bizzwords/ios/128.png": "a633c3057d9b8aa325c39ada1914f32a84a35003",
    "https://looted.github.io/bizzwords/ios/144.png": "b8353db625e8525effc2342cc05a80bf52758675",
    "https://looted.github.io/bizzwords/ios/152.png": "232a2270badcf5a70efd96a526d95f438d0d62a6",
    "https://looted.github.io/bizzwords/ios/16.png": "5c0037b236efb53012ce487750734c6d970d255a",
    "https://looted.github.io/bizzwords/ios/167.png": "2cdfe042a5048f5dde9f341007c94ee521886e15",
    "https://looted.github.io/bizzwords/ios/180.png": "1020769316fbe5e5660eb646a493026801201a35",
    "https://looted.github.io/bizzwords/ios/192.png": "d817709e32dd5432b999afd08f46fd92d63d429e",
    "https://looted.github.io/bizzwords/ios/20.png": "3e0835f0a617ac6bd947a48fe64b337754269e3c",
    "https://looted.github.io/bizzwords/ios/256.png": "3ee8715403a2e80930bf11b5d7e9759b2c02b3a0",
    "https://looted.github.io/bizzwords/ios/29.png": "730c7b9799ed9a9f7df0040f84ca81f73b78ffaa",
    "https://looted.github.io/bizzwords/ios/32.png": "24ca7d3e21d15bc8d645bf5c76360767d690b5ce",
    "https://looted.github.io/bizzwords/ios/40.png": "2c11a7f5185a18d63ebf56c5b6f84de780a75c2b",
    "https://looted.github.io/bizzwords/ios/50.png": "3f1bb495d7d295327525c83a14145aa1f65db661",
    "https://looted.github.io/bizzwords/ios/512.png": "b3e3b35559fd519ae9b484a814fb895ec7403e50",
    "https://looted.github.io/bizzwords/ios/57.png": "138c884f5daa1323bd32f200be787b5f74f47028",
    "https://looted.github.io/bizzwords/ios/58.png": "e6587e50b043feb9954211a152ab371003781ac2",
    "https://looted.github.io/bizzwords/ios/60.png": "6a4b2f38543b446fa2d1953c2fe4290759efbe88",
    "https://looted.github.io/bizzwords/ios/64.png": "6036414a1bc19f5358d4928b8effb727d563904c",
    "https://looted.github.io/bizzwords/ios/72.png": "8152c13d0cf1aec370a37730bf9d57989e47b59b",
    "https://looted.github.io/bizzwords/ios/76.png": "f695db1227e9315ccabcfc0a4f059efdee3d36be",
    "https://looted.github.io/bizzwords/ios/80.png": "edcaa31f90ac6db11a5805a27ac2f6012452acb7",
    "https://looted.github.io/bizzwords/ios/87.png": "05552082838274e1b519f6de6cc902ac409d1486",
    "https://looted.github.io/bizzwords/main-BPGW77ZI.js": "85df2787b08c252dc77c400d2cbb25743c3456f9",
    "https://looted.github.io/bizzwords/manifest.webmanifest": "6b76ba0ecdf9948c8a3551caf6aa292acbbde526",
    "https://looted.github.io/bizzwords/styles-BIIUBW6Z.css": "c48c1f17950ffa4f8b85c9ab06bab8d3bb1199a4",
    "https://looted.github.io/bizzwords/windows11/LargeTile.scale-100.png": "dab179986ce37aeeca1bd8eba16df1476629aed5",
    "https://looted.github.io/bizzwords/windows11/LargeTile.scale-125.png": "02b4794a71cb7f69f5e0c294cae62ea78a9056f1",
    "https://looted.github.io/bizzwords/windows11/LargeTile.scale-150.png": "75f9ac49681f1439283dc0a6dedaf6d1edd92e96",
    "https://looted.github.io/bizzwords/windows11/LargeTile.scale-200.png": "5f4ce8b2a3753ff6e1c8f7e1a1a6dc06a018acf9",
    "https://looted.github.io/bizzwords/windows11/LargeTile.scale-400.png": "d68a0e19486972378ee07a295bed661df6ede5ae",
    "https://looted.github.io/bizzwords/windows11/SmallTile.scale-100.png": "91f2c063fd7f5fcd06d2d53c42785b5cd7172213",
    "https://looted.github.io/bizzwords/windows11/SmallTile.scale-125.png": "c903d16eaa06598a3e581cb5fa4a2c6a4c1ad557",
    "https://looted.github.io/bizzwords/windows11/SmallTile.scale-150.png": "dbaa7d506b650cfc823f09bb0135ee135da258f5",
    "https://looted.github.io/bizzwords/windows11/SmallTile.scale-200.png": "84580065da091da832cb04437a27563e39b57a9d",
    "https://looted.github.io/bizzwords/windows11/SmallTile.scale-400.png": "5a2bbecda39aaf36e1bf08aa12feee5189cf841e",
    "https://looted.github.io/bizzwords/windows11/SplashScreen.scale-100.png": "24243e6246a057ca5d27c24587d9ff2f7db1555d",
    "https://looted.github.io/bizzwords/windows11/SplashScreen.scale-125.png": "541acc211dfe79507ffe73451aea670eb39ad445",
    "https://looted.github.io/bizzwords/windows11/SplashScreen.scale-150.png": "7d4580bcc2b413620ecc7fe8e0851446e82deb9c",
    "https://looted.github.io/bizzwords/windows11/SplashScreen.scale-200.png": "7248aedd81945719b4582cd89cde05f02aac3eba",
    "https://looted.github.io/bizzwords/windows11/SplashScreen.scale-400.png": "de95d297d39d38de4a4c281d502be76481da7838",
    "https://looted.github.io/bizzwords/windows11/Square150x150Logo.scale-100.png": "8f6706187acf9518fb172eac006d33fa30a0b61c",
    "https://looted.github.io/bizzwords/windows11/Square150x150Logo.scale-125.png": "9c81cad69e2af7e361c07ee534b74b8ceba3b183",
    "https://looted.github.io/bizzwords/windows11/Square150x150Logo.scale-150.png": "f175cebb17cb9365ca033a6986ad69196e640212",
    "https://looted.github.io/bizzwords/windows11/Square150x150Logo.scale-200.png": "1da568ae1865de0e42629af5b796152e2e2c3107",
    "https://looted.github.io/bizzwords/windows11/Square150x150Logo.scale-400.png": "7f018f96a8165719afe7bdb964155b5aac15275d",
    "https://looted.github.io/bizzwords/windows11/Square44x44Logo.altform-lightunplated_targetsize-16.png": "3a2cb1a5f6c718591ee5c6eafcd3047c825eab72",
    "https://looted.github.io/bizzwords/windows11/Square44x44Logo.altform-lightunplated_targetsize-20.png": "e9957b8ca6514d538a99ebc5a4e902147b97caa2",
    "https://looted.github.io/bizzwords/windows11/Square44x44Logo.altform-lightunplated_targetsize-24.png": "c943d64cbf5092d0ef7953c75e31d0de101f41f9",
    "https://looted.github.io/bizzwords/windows11/Square44x44Logo.altform-lightunplated_targetsize-256.png": "56982cda6e6eacde08c58303997afea9e49b91d2",
    "https://looted.github.io/bizzwords/windows11/Square44x44Logo.altform-lightunplated_targetsize-30.png": "cd3e221e3cbca14a1f17c325ac8403430c65acae",
    "https://looted.github.io/bizzwords/windows11/Square44x44Logo.altform-lightunplated_targetsize-32.png": "ed030d881a0c81d799e049ed1438a01f87367b47",
    "https://looted.github.io/bizzwords/windows11/Square44x44Logo.altform-lightunplated_targetsize-36.png": "2b3a7c53ee513fd7ac1da489c421468f3c2c9826",
    "https://looted.github.io/bizzwords/windows11/Square44x44Logo.altform-lightunplated_targetsize-40.png": "edf1b9917ba14f1b8e50494ae56fc827a0a45344",
    "https://looted.github.io/bizzwords/windows11/Square44x44Logo.altform-lightunplated_targetsize-44.png": "528cf7df3fa3b6b6187e5ef84d9aae67190c5e7d",
    "https://looted.github.io/bizzwords/windows11/Square44x44Logo.altform-lightunplated_targetsize-48.png": "ceee4f631c0d7ae78fb095018b6af19b3b5c842e",
    "https://looted.github.io/bizzwords/windows11/Square44x44Logo.altform-lightunplated_targetsize-60.png": "93c4076c7e3cb4974a2841275a66dfc7f1ba4bcd",
    "https://looted.github.io/bizzwords/windows11/Square44x44Logo.altform-lightunplated_targetsize-64.png": "2540a2ba11751a7a7034bde4c3e7be9a2bb75c41",
    "https://looted.github.io/bizzwords/windows11/Square44x44Logo.altform-lightunplated_targetsize-72.png": "09dd923cad69bff6c05708e0d860f5a1acd23919",
    "https://looted.github.io/bizzwords/windows11/Square44x44Logo.altform-lightunplated_targetsize-80.png": "373bfb9e6664d45f3be9daf951965841eeb421e2",
    "https://looted.github.io/bizzwords/windows11/Square44x44Logo.altform-lightunplated_targetsize-96.png": "c494bdc975f58f05d9734f610a7bacf039089c28",
    "https://looted.github.io/bizzwords/windows11/Square44x44Logo.altform-unplated_targetsize-16.png": "3a2cb1a5f6c718591ee5c6eafcd3047c825eab72",
    "https://looted.github.io/bizzwords/windows11/Square44x44Logo.altform-unplated_targetsize-20.png": "e9957b8ca6514d538a99ebc5a4e902147b97caa2",
    "https://looted.github.io/bizzwords/windows11/Square44x44Logo.altform-unplated_targetsize-24.png": "c943d64cbf5092d0ef7953c75e31d0de101f41f9",
    "https://looted.github.io/bizzwords/windows11/Square44x44Logo.altform-unplated_targetsize-256.png": "56982cda6e6eacde08c58303997afea9e49b91d2",
    "https://looted.github.io/bizzwords/windows11/Square44x44Logo.altform-unplated_targetsize-30.png": "cd3e221e3cbca14a1f17c325ac8403430c65acae",
    "https://looted.github.io/bizzwords/windows11/Square44x44Logo.altform-unplated_targetsize-32.png": "ed030d881a0c81d799e049ed1438a01f87367b47",
    "https://looted.github.io/bizzwords/windows11/Square44x44Logo.altform-unplated_targetsize-36.png": "2b3a7c53ee513fd7ac1da489c421468f3c2c9826",
    "https://looted.github.io/bizzwords/windows11/Square44x44Logo.altform-unplated_targetsize-40.png": "edf1b9917ba14f1b8e50494ae56fc827a0a45344",
    "https://looted.github.io/bizzwords/windows11/Square44x44Logo.altform-unplated_targetsize-44.png": "528cf7df3fa3b6b6187e5ef84d9aae67190c5e7d",
    "https://looted.github.io/bizzwords/windows11/Square44x44Logo.altform-unplated_targetsize-48.png": "ceee4f631c0d7ae78fb095018b6af19b3b5c842e",
    "https://looted.github.io/bizzwords/windows11/Square44x44Logo.altform-unplated_targetsize-60.png": "93c4076c7e3cb4974a2841275a66dfc7f1ba4bcd",
    "https://looted.github.io/bizzwords/windows11/Square44x44Logo.altform-unplated_targetsize-64.png": "2540a2ba11751a7a7034bde4c3e7be9a2bb75c41",
    "https://looted.github.io/bizzwords/windows11/Square44x44Logo.altform-unplated_targetsize-72.png": "09dd923cad69bff6c05708e0d860f5a1acd23919",
    "https://looted.github.io/bizzwords/windows11/Square44x44Logo.altform-unplated_targetsize-80.png": "373bfb9e6664d45f3be9daf951965841eeb421e2",
    "https://looted.github.io/bizzwords/windows11/Square44x44Logo.altform-unplated_targetsize-96.png": "c494bdc975f58f05d9734f610a7bacf039089c28",
    "https://looted.github.io/bizzwords/windows11/Square44x44Logo.scale-100.png": "528cf7df3fa3b6b6187e5ef84d9aae67190c5e7d",
    "https://looted.github.io/bizzwords/windows11/Square44x44Logo.scale-125.png": "788adbab10c0e4c25167420277d792735e7bf215",
    "https://looted.github.io/bizzwords/windows11/Square44x44Logo.scale-150.png": "925633f4a65085dd89fb75ca011e21f263938ae6",
    "https://looted.github.io/bizzwords/windows11/Square44x44Logo.scale-200.png": "69bbed29995f7d40a2bde14b1b05b0a3b277869d",
    "https://looted.github.io/bizzwords/windows11/Square44x44Logo.scale-400.png": "b68693e212a5aa598ba1395480a5ac8597cb6b98",
    "https://looted.github.io/bizzwords/windows11/Square44x44Logo.targetsize-16.png": "3a2cb1a5f6c718591ee5c6eafcd3047c825eab72",
    "https://looted.github.io/bizzwords/windows11/Square44x44Logo.targetsize-20.png": "e9957b8ca6514d538a99ebc5a4e902147b97caa2",
    "https://looted.github.io/bizzwords/windows11/Square44x44Logo.targetsize-24.png": "c943d64cbf5092d0ef7953c75e31d0de101f41f9",
    "https://looted.github.io/bizzwords/windows11/Square44x44Logo.targetsize-256.png": "56982cda6e6eacde08c58303997afea9e49b91d2",
    "https://looted.github.io/bizzwords/windows11/Square44x44Logo.targetsize-30.png": "cd3e221e3cbca14a1f17c325ac8403430c65acae",
    "https://looted.github.io/bizzwords/windows11/Square44x44Logo.targetsize-32.png": "ed030d881a0c81d799e049ed1438a01f87367b47",
    "https://looted.github.io/bizzwords/windows11/Square44x44Logo.targetsize-36.png": "2b3a7c53ee513fd7ac1da489c421468f3c2c9826",
    "https://looted.github.io/bizzwords/windows11/Square44x44Logo.targetsize-40.png": "edf1b9917ba14f1b8e50494ae56fc827a0a45344",
    "https://looted.github.io/bizzwords/windows11/Square44x44Logo.targetsize-44.png": "528cf7df3fa3b6b6187e5ef84d9aae67190c5e7d",
    "https://looted.github.io/bizzwords/windows11/Square44x44Logo.targetsize-48.png": "ceee4f631c0d7ae78fb095018b6af19b3b5c842e",
    "https://looted.github.io/bizzwords/windows11/Square44x44Logo.targetsize-60.png": "93c4076c7e3cb4974a2841275a66dfc7f1ba4bcd",
    "https://looted.github.io/bizzwords/windows11/Square44x44Logo.targetsize-64.png": "2540a2ba11751a7a7034bde4c3e7be9a2bb75c41",
    "https://looted.github.io/bizzwords/windows11/Square44x44Logo.targetsize-72.png": "09dd923cad69bff6c05708e0d860f5a1acd23919",
    "https://looted.github.io/bizzwords/windows11/Square44x44Logo.targetsize-80.png": "373bfb9e6664d45f3be9daf951965841eeb421e2",
    "https://looted.github.io/bizzwords/windows11/Square44x44Logo.targetsize-96.png": "c494bdc975f58f05d9734f610a7bacf039089c28",
    "https://looted.github.io/bizzwords/windows11/StoreLogo.scale-100.png": "98882501bf194f47595d1b02d6aa09ff22031c1a",
    "https://looted.github.io/bizzwords/windows11/StoreLogo.scale-125.png": "7bebf34d7756ffb5e80f809eeb91bc3aaefc90b2",
    "https://looted.github.io/bizzwords/windows11/StoreLogo.scale-150.png": "5bcd895cfed3e229c5a12e4ac829182927abe6d8",
    "https://looted.github.io/bizzwords/windows11/StoreLogo.scale-200.png": "9599e0d45072e931c665ad0cd3c82ec148be8449",
    "https://looted.github.io/bizzwords/windows11/StoreLogo.scale-400.png": "f8ba1b6228b326696a67d2941066eb50129746cd",
    "https://looted.github.io/bizzwords/windows11/Wide310x150Logo.scale-100.png": "39953befaa20415aba558cf97ecf7ee8c4cadba4",
    "https://looted.github.io/bizzwords/windows11/Wide310x150Logo.scale-125.png": "aeb3b64047ffcf7eeac7c84d82c147b27721f0df",
    "https://looted.github.io/bizzwords/windows11/Wide310x150Logo.scale-150.png": "4437ada9a96edce27d29f7be03170116ac84131c",
    "https://looted.github.io/bizzwords/windows11/Wide310x150Logo.scale-200.png": "24243e6246a057ca5d27c24587d9ff2f7db1555d",
    "https://looted.github.io/bizzwords/windows11/Wide310x150Logo.scale-400.png": "7248aedd81945719b4582cd89cde05f02aac3eba",
    "https://looted.github.io/bizzwords/worker-FORKZ3OH.js": "755a45c86463aa596db5678d99a3ed32f639dc93"
  },
  "navigationUrls": [
    {
      "positive": true,
      "regex": "^\\/.*$"
    },
    {
      "positive": false,
      "regex": "^\\/(?:.+\\/)?[^/]*\\.[^/]*$"
    },
    {
      "positive": false,
      "regex": "^\\/(?:.+\\/)?[^/]*__[^/]*$"
    },
    {
      "positive": false,
      "regex": "^\\/(?:.+\\/)?[^/]*__[^/]*\\/.*$"
    }
  ],
  "navigationRequestStrategy": "performance"
}